{
 "fetched_at": "2026-07-22T15:20:54+00:00",
 "vix": 17.0,
 "vix_prev": 19.49,
 "tnx_pct": 4.65,
 "tnx_prev_pct": 4.49,
 "rate_dir": "rising",
 "spx": 7516.35,
 "spx_up": true,
 "ndx": 29153.5,
 "world": 203.37,
 "dxy": 101.11,
 "oil": 87.09,
 "gold": 4159.6,
 "copper": 6.51,
 "silver": 60.64,
 "btc": 66007.49,
 "dxy_dir": "flat",
 "oil_dir": "rising",
 "gold_dir": "flat",
 "copper_dir": "rising",
 "silver_dir": "flat",
 "btc_dir": "rising",
 "regime": "neutral",
 "regime_label": "neutral",
 "fomc_next": "2026-07-29",
 "fomc_in_days": 7,
 "fomc_tone": {
  "tone": "dovish",
  "headline": "Federal Reserve announces the leadership and objectives of its task forces to advance the conduct of monetary policy",
  "date": "<![CDATA[Thu, 9 "
 }
}